LICENSE
README.md
setup.py
pyshield/__init__.py
pyshield/funcs.py
pyshield/helpers.py
pyshield/pyshield.py
pyshield.egg-info/PKG-INFO
pyshield.egg-info/SOURCES.txt
pyshield.egg-info/dependency_links.txt
pyshield.egg-info/entry_points.txt
pyshield.egg-info/requires.txt
pyshield.egg-info/top_level.txt
pyshield/cli/__init__.py