Metadata-Version: 2.1
Name: pyshield
Version: 0.0.7
Summary: Hard Obfuscate Tool For Python
Home-page: https://github.com/0xe2d0/pyshield
Author: 0xe2d0
License: MIT
Download-URL: https://github.com/0xe2d0/pyshield/tarball/master
Keywords: obfuscator,python-obfuscate,pyshield,python code obfuscate
Platform: UNKNOWN
Classifier: Development Status :: 1 - Planning
Classifier: Intended Audience :: Developers
Classifier: Topic :: Software Development :: Build Tools
Classifier: License :: OSI Approved :: MIT License
Classifier: Programming Language :: Python :: 3.6
Classifier: Programming Language :: Python :: 3.7
Classifier: Programming Language :: Python :: 3.8
Classifier: Programming Language :: Python :: 3.9
License-File: LICENSE
